needed_libs/__init__.py
needed_libs-2.4.dist-info/METADATA
needed_libs-2.4.dist-info/WHEEL
needed_libs-2.4.dist-info/top_level.txt
needed_libs-2.4.dist-info/RECORD
