Metadata-Version: 2.2
Name: needed-libs
Version: 2.4
Requires-Dist: websocket-client
Requires-Dist: httpx
Requires-Dist: requests
Requires-Dist: python_ghost_cursor
Requires-Dist: price_parser
Requires-Dist: pywin32
Requires-Dist: python-timeout
Requires-Dist: python-printr
Requires-Dist: error_alerts
Requires-Dist: python-objectifier
Requires-Dist: python-window-recorder
Requires-Dist: tweepy
Requires-Dist: python-twitter
Requires-Dist: praw
Requires-Dist: instagrapi
Requires-Dist: moviepy
Requires-Dist: telethon
Requires-Dist: yt-dlp
Requires-Dist: requestium
Requires-Dist: feedparser
Requires-Dist: bs4
Requires-Dist: selenium-shortcuts
Requires-Dist: python-slugify
Requires-Dist: anticaptchaofficial
Requires-Dist: openai
Requires-Dist: gspread
Requires-Dist: google-api-python-client
Requires-Dist: google_auth_oauthlib
Requires-Dist: google
Requires-Dist: flask
Requires-Dist: waitress
Requires-Dist: requests-futures
Requires-Dist: schedule
Requires-Dist: demoji
Requires-Dist: ffprobe-python
Requires-Dist: python-dateutil
Requires-Dist: dateparser
Requires-Dist: pathvalidate
Requires-Dist: inflect
Requires-Dist: betfairlightweight
Requires-Dist: websockets
Dynamic: requires-dist
